Workbook

Sheet Purchases
A1: Farm-Bike Budget Sheet — Confirmed Purchases
A3: Date | B3: Supplier | C3: Invoice / Receipt | D3: Category | E3: Reference | F3: Item / Description | G3: Qty | H3: Total incl. VAT/shipping (CHF)
A4: 46112 | B4: norelem Normelemente AG | C4: 3210081379 | D4: Belt & pulley transmission | E4: 23200-0382522 | F4: Taper-lock bushing 1108, 22.3×25, D=38, cast iron | G4: 1 | H4: 6.25
A5: 46112 | B5: norelem Normelemente AG | C5: 3210081379 | D5: Belt & pulley transmission | E5: 22070-12711 | F5: V-belt pulley SPZ/10/Z, taper-lock, D=71, N=1, cast iron | G5: 1 | H5: 7.48
A6: 46112 | B6: norelem Normelemente AG | C6: 3210081379 | D6: Belt & pulley transmission | E6: 22070-11181 | F6: V-belt pulley SPZ/10/Z, taper-lock, D=118, N=1, cast iron | G6: 3 | H6: 39.22
A7: 46112 | B7: norelem Normelemente AG | C7: 3210081379 | D7: Belt & pulley transmission | E7: 22071-12080 | F7: V-belt DIN2215, type 10/Z, Li=2080, Br=10, neoprene | G7: 1 | H7: 20.74
A8: 46112 | B8: norelem Normelemente AG | C8: 3210081379 | D8: Belt & pulley transmission | E8: 23200-0572225 | F8: Taper-lock bushing 1610, 25.4×22, D=57, cast iron | G8: 1 | H8: 9.01
A9: 46112 | B9: norelem Normelemente AG | C9: 3210081379 | D9: Bearings & drivetrain support | E9: 23800-102504712 | F9: FAG deep-groove ball bearing 6005-2Z, 25×47×12 | G9: 2 | H9: 23.95
A10: 46112 | B10: norelem Normelemente AG | C10: 3210081379 | D10: Keys, fasteners & mounting | E10: 03288-08X45 | F10: DIN6885 parallel key, form A, B=8, L=45, H=7 | G10: 3 | H10: 2.06
A11: 46112 | B11: norelem Normelemente AG | C11: 3210081379 | D11: Adhesives & consumables | E11: 97990-6030010 | F11: Loctite 603 retaining compound, 10 ml | G11: 1 | H11: 27.1
A12: 46112 | B12: norelem Normelemente AG | C12: 3210081379 | D12: Belt & pulley transmission | E12: 23200-0571425 | F12: Taper-lock bushing 1610, 25.4×14, D=57, cast iron | G12: 2 | H12: 18.03
A13: 46112 | B13: norelem Normelemente AG | C13: 3210081379 | D13: Keys, fasteners & mounting | E13: 29014-30 | F13: Tube clamp/bracket, M=80, G=50, L=62.5, A=30 | G13: 2 | H13: 11.23
A14: 46112 | B14: norelem Normelemente AG | C14: 3210081379 | D14: Keys, fasteners & mounting | E14: 27616-08095 | F14: Fixing support, form B long, zinc-plated steel, L=95, A=75 | G14: 1 | H14: 6.79
A15: 46125 | B15: EPFL Point Vélo | C15: Receipt 9900000288211 | D15: Bicycle components | F15: Second-hand bicycle material | G15: 1 | H15: 45
H16: =SUM(PurchasesTable[Total incl. VAT/shipping (CHF)]) -> 216.86

Sheet Dashboard
A1: Farm-Bike Project Budget Summary
A3: Metric | B3: Value | D3: Category | E3: Subtotal excl. VAT | F3: Total incl. VAT/shipping
A4: Confirmed total paid (incl. VAT + shipping) | B4: =SUM(Purchases!M:M) -> 0 | D4: Belt & pulley transmission | E4: =SUMIFS(Purchases!$J:$J,Purchases!$D:$D,D4) -> 0 | F4: =SUMIFS(Purchases!$M:$M,Purchases!$D:$D,D4) -> 0
A5: Norelem subtotal excl. VAT | B5: =SUMIFS(Purchases!J:J,Purchases!B:B,"norelem Normelemente AG") -> 0 | D5: Bearings & drivetrain support | E5: =SUMIFS(Purchases!$J:$J,Purchases!$D:$D,D5) -> 0 | F5: =SUMIFS(Purchases!$M:$M,Purchases!$D:$D,D5) -> 0
A6: Norelem shipping | B6: 28.95 | D6: Keys, fasteners & mounting | E6: =SUMIFS(Purchases!$J:$J,Purchases!$D:$D,D6) -> 0 | F6: =SUMIFS(Purchases!$M:$M,Purchases!$D:$D,D6) -> 0
A7: Norelem VAT | B7: 12.88 | D7: Adhesives & consumables | E7: =SUMIFS(Purchases!$J:$J,Purchases!$D:$D,D7) -> 0 | F7: =SUMIFS(Purchases!$M:$M,Purchases!$D:$D,D7) -> 0
A8: Norelem total | B8: =SUMIFS(Purchases!M:M,Purchases!B:B,"norelem Normelemente AG") -> 0 | D8: Bicycle components | E8: =SUMIFS(Purchases!$J:$J,Purchases!$D:$D,D8) -> 0 | F8: =SUMIFS(Purchases!$M:$M,Purchases!$D:$D,D8) -> 0
A9: Point Vélo total | B9: =SUMIFS(Purchases!M:M,Purchases!B:B,"EPFL Point Vélo") -> 0
A10: Number of purchase lines | B10: =COUNTA(Purchases!F:F)-1 -> 12 | D10: TOTAL | E10: =SUM(E4:E8) -> 0 | F10: =SUM(F4:F8) -> 0
A12: Scope note
A13: This budget is based on the purchase evidence included in the uploaded project folder: the Norelem order confirmation and the EPFL Point Vélo receipt. Recovered parts, donated parts, off-cuts, Item profiles recovered from decommissioned machinery and workshop labour are listed separately and excluded from the confirmed paid total unless a price is added later.

Sheet Recovered_or_Excluded
A1: Recovered / In-kind / Not Priced Items
A3: Category | B3: Item | C3: Source / evidence | D3: Qty | E3: Unit value estimate (CHF) | F3: Total estimate (CHF) | G3: Budget treatment
A4: Frame structure | B4: Item Profile 8 aluminium profiles and relevant hardware | C4: Report/README: recovered from decommissioned machinery | F4: =IF(OR(D4="",E4=""),"",D4*E4) | G4: Excluded from confirmed purchases
A5: Stock material | B5: 6061 aluminium billet/off-cuts for pillow block | C5: Report/README: material off-cuts/scrapped parts used where possible | F5: =IF(OR(D5="",E5=""),"",D5*E5) | G5: Excluded unless price is added
A6: Stock material | B6: S235 steel plate/off-cut for flywheel | C6: Report: flywheel cut from 5 mm S235 structural steel off-cut | F6: =IF(OR(D6="",E6=""),"",D6*E6) | G6: Excluded unless price is added
A7: Bicycle frame donor | B7: Donor bicycle frame with BSA bottom bracket shell | C7: Report/README: recovered from donor frame | D7: 1 | F7: =IF(OR(D7="",E7=""),"",D7*E7) | G7: Excluded / recovered
A8: Bicycle drivetrain | B8: Cassette, derailleur, shifter, handlebars, stem, crankset, bottom bracket, seatpost, saddle | C8: Report/README and Point Vélo receipt; detailed line split unavailable | F8: =IF(OR(D8="",E8=""),"",D8*E8) | G8: Partly covered by Point Vélo lump-sum receipt
A9: Workshop resources | B9: Machining, TIG welding, laser cutting, assembly labour | C9: Project fabrication work; no purchase evidence in folder | F9: =IF(OR(D9="",E9=""),"",D9*E9) | G9: Excluded from material budget

Sheet Sources
A1: Source Documents Used
A3: Source file | B3: Supplier / document | C3: Key amounts extracted | D3: Notes
A4: Documentation/Confirmation.de.commande.norelem.3210081379.-.Redacted.pdf | B4: norelem order confirmation 3210081379, dated 2026-03-31 | C4: Subtotal 130.03 CHF; shipping 28.95 CHF; VAT 12.88 CHF; total 171.86 CHF | D4: Line items copied from order confirmation
A5: Documentation/Facture point velo EPFL.JPG | B5: EPFL Point Vélo receipt, dated 2026-04-13 | C5: Net 41.63 CHF; VAT 3.37 CHF; total 45.00 CHF | D5: Receipt only lists one lump-sum line: Divers Matériel occa
A6: Documentation/Farm_Bike_may25th2026.pdf and README.md | B6: Project report / README | C6: Recovered parts and no-cost items identified | D6: Used to separate confirmed purchases from in-kind materials
